{"file:///c%3A/Users/Jack/Desktop/Web%20Serveur/Projet%20partie%202/partie2/package.json":{"language":"JSON","code":33,"comment":0,"blank":1},"file:///c%3A/Users/Jack/Desktop/Web%20Serveur/Projet%20partie%202/partie2/server.js":{"language":"JavaScript","code":262,"comment":19,"blank":57},"file:///c%3A/Users/Jack/Desktop/Web%20Serveur/Projet%20partie%202/partie2/validationAjoutCours.js":{"language":"JavaScript","code":29,"comment":8,"blank":11},"file:///c%3A/Users/Jack/Desktop/Web%20Serveur/Projet%20partie%202/partie2/validationInscription.js":{"language":"JavaScript","code":22,"comment":22,"blank":10},"file:///c%3A/Users/Jack/Desktop/Web%20Serveur/Projet%20partie%202/partie2/public/js/connexion.js":{"language":"JavaScript","code":55,"comment":5,"blank":10},"file:///c%3A/Users/Jack/Desktop/Web%20Serveur/Projet%20partie%202/partie2/systeme.db":{"language":"Database","code":76,"comment":0,"blank":2},"file:///c%3A/Users/Jack/Desktop/Web%20Serveur/Projet%20partie%202/partie2/public/js/compte.js":{"language":"JavaScript","code":36,"comment":0,"blank":15},"file:///c%3A/Users/Jack/Desktop/Web%20Serveur/Projet%20partie%202/partie2/public/js/cours.js":{"language":"JavaScript","code":34,"comment":0,"blank":13},"file:///c%3A/Users/Jack/Desktop/Web%20Serveur/Projet%20partie%202/partie2/public/js/admin.js":{"language":"JavaScript","code":230,"comment":11,"blank":63},"file:///c%3A/Users/Jack/Desktop/Web%20Serveur/Projet%20partie%202/partie2/public/js/accept-cookie.js":{"language":"JavaScript","code":12,"comment":0,"blank":3},"file:///c%3A/Users/Jack/Desktop/Web%20Serveur/Projet%20partie%202/partie2/public/js/accueil.js":{"language":"JavaScript","code":0,"comment":0,"blank":1},"file:///c%3A/Users/Jack/Desktop/Web%20Serveur/Projet%20partie%202/partie2/public/js/methode-commune.js":{"language":"JavaScript","code":83,"comment":3,"blank":36},"file:///c%3A/Users/Jack/Desktop/Web%20Serveur/Projet%20partie%202/partie2/public/js/inscription.js":{"language":"JavaScript","code":84,"comment":16,"blank":15},"file:///c%3A/Users/Jack/Desktop/Web%20Serveur/Projet%20partie%202/partie2/public/css/style.css":{"language":"CSS","code":59,"comment":0,"blank":13},"file:///c%3A/Users/Jack/Desktop/Web%20Serveur/Projet%20partie%202/partie2/public/css/general.css":{"language":"CSS","code":73,"comment":0,"blank":19},"file:///c%3A/Users/Jack/Desktop/Web%20Serveur/Projet%20partie%202/partie2/public/css/normalize.css":{"language":"CSS","code":146,"comment":159,"blank":74},"file:///c%3A/Users/Jack/Desktop/Web%20Serveur/Projet%20partie%202/partie2/views/cours.handlebars":{"language":"Handlebars","code":31,"comment":0,"blank":1},"file:///c%3A/Users/Jack/Desktop/Web%20Serveur/Projet%20partie%202/partie2/views/compte.handlebars":{"language":"Handlebars","code":32,"comment":0,"blank":0},"file:///c%3A/Users/Jack/Desktop/Web%20Serveur/Projet%20partie%202/partie2/views/inscription.handlebars":{"language":"Handlebars","code":43,"comment":6,"blank":7},"file:///c%3A/Users/Jack/Desktop/Web%20Serveur/Projet%20partie%202/partie2/views/connexion.handlebars":{"language":"Handlebars","code":38,"comment":5,"blank":6},"file:///c%3A/Users/Jack/Desktop/Web%20Serveur/Projet%20partie%202/partie2/views/admin.handlebars":{"language":"Handlebars","code":162,"comment":2,"blank":14},"file:///c%3A/Users/Jack/Desktop/Web%20Serveur/Projet%20partie%202/partie2/views/accueil.handlebars":{"language":"Handlebars","code":14,"comment":0,"blank":3},"file:///c%3A/Users/Jack/Desktop/Web%20Serveur/Projet%20partie%202/partie2/views/layouts/main.handlebars":{"language":"Handlebars","code":41,"comment":0,"blank":11},"file:///c%3A/Users/Jack/Desktop/Web%20Serveur/Projet%20partie%202/partie2/views/partials/footer.handlebars":{"language":"Handlebars","code":16,"comment":0,"blank":0},"file:///c%3A/Users/Jack/Desktop/Web%20Serveur/Projet%20partie%202/partie2/model/utilisateur.js":{"language":"JavaScript","code":0,"comment":4,"blank":0},"file:///c%3A/Users/Jack/Desktop/Web%20Serveur/Projet%20partie%202/partie2/views/partials/header.handlebars":{"language":"Handlebars","code":40,"comment":0,"blank":4},"file:///c%3A/Users/Jack/Desktop/Web%20Serveur/Projet%20partie%202/partie2/package-lock.json":{"language":"JSON","code":4367,"comment":0,"blank":1},"file:///c%3A/Users/Jack/Desktop/Web%20Serveur/Projet%20partie%202/partie2/model/methodeServeur.js":{"language":"JavaScript","code":176,"comment":0,"blank":69},"file:///c%3A/Users/Jack/Desktop/Web%20Serveur/Projet%20partie%202/partie2/model/connexion.js":{"language":"JavaScript","code":99,"comment":11,"blank":15},"file:///c%3A/Users/Jack/Desktop/Web%20Serveur/Projet%20partie%202/partie2/authentification.js":{"language":"JavaScript","code":40,"comment":0,"blank":12},"file:///c%3A/Users/Jack/Desktop/Web%20Serveur/Projet%20partie%202/partie2/middlewareSse.js":{"language":"JavaScript","code":35,"comment":15,"blank":9}}